Litindex.py
__init__.py
exception.py
Litindex-0.0.3.dist-info/METADATA
Litindex-0.0.3.dist-info/WHEEL
Litindex-0.0.3.dist-info/top_level.txt
Litindex-0.0.3.dist-info/RECORD
